zsearch.py
zsearch-1.2.dist-info/METADATA
zsearch-1.2.dist-info/WHEEL
zsearch-1.2.dist-info/top_level.txt
zsearch-1.2.dist-info/RECORD
