Metadata-Version: 2.1
Name: zsearch
Version: 1.2
Summary: The Head First Python Search Tools
Home-page: https://github.com/azeltov/adb_workshop
Author: HF Python 2e
Author-email: azeltov@gmail.com
License: UNKNOWN
Platform: UNKNOWN
Requires-Python: >=3.6
